compost_rpc/__init__.py
compost_rpc/__main__.py
compost_rpc/compost_rpc.py
compost_rpc/lib/c/header_template.py
compost_rpc/lib/c/source_template.py
compost_rpc-0.6.0.dist-info/licenses/LICENSE
compost_rpc-0.6.0.dist-info/WHEEL
compost_rpc-0.6.0.dist-info/METADATA
compost_rpc-0.6.0.dist-info/RECORD
