Metadata-Version: 2.4
Name: compost-rpc
Version: 0.6.0
Summary: Compost RPC protocol generator
Keywords: protocol,RPC,MCU,embedded
Author: Radovan Blažek, Petr Moucha
Author-email: Radovan Blažek <radovan.blazek@st.com>, Petr Moucha <petr.moucha@st.com>
License-Expression: BSD-3-Clause
License-File: LICENSE
Requires-Dist: colorful==0.5.* ; extra == 'addons'
Requires-Dist: sphinx==8.1.3 ; extra == 'docs'
Requires-Dist: myst-parser==4.0.1 ; extra == 'docs'
Requires-Dist: furo==2024.8.6 ; extra == 'docs'
Requires-Dist: breathe==4.36.0 ; extra == 'docs'
Requires-Dist: pyserial==3.* ; extra == 'serial'
Requires-Dist: pytest==8.3.* ; extra == 'test'
Requires-Python: >=3.10
Project-URL: Issues, https://github.com/STMicroelectronics/compost-rpc/issues
Project-URL: Source, https://github.com/STMicroelectronics/compost-rpc
Project-URL: documentation, https://github.com/STMicroelectronics/compost-rpc/wiki
Provides-Extra: addons
Provides-Extra: docs
Provides-Extra: serial
Provides-Extra: test
